instaspy/__init__.py
instaspy/instaspy.py
instaspy_pip-1.0.dist-info/METADATA
instaspy_pip-1.0.dist-info/WHEEL
instaspy_pip-1.0.dist-info/entry_points.txt
instaspy_pip-1.0.dist-info/top_level.txt
instaspy_pip-1.0.dist-info/RECORD
