Metadata-Version: 2.1
Name: instaspy-pip
Version: 1.0
Summary: A tool to fetch Instagram user data and media.
Home-page: https://github.com/IM-SPYBOY/instaspy
Author: spyboy
Author-email: spyboy.co@gmail.com
Classifier: Programming Language :: Python :: 3
Classifier: License :: OSI Approved :: MIT License
Classifier: Operating System :: OS Independent
Requires-Python: >=3.6
Requires-Dist: requests
Requires-Dist: instagrapi
Requires-Dist: googlesearch-python
Requires-Dist: colorama
Requires-Dist: termcolor
